{
  "db_name": "PostgreSQL",
  "query": "\n            UPDATE contents\n            SET\n                title = COALESCE($3, title),\n                description = CASE\n                    WHEN $4::bool THEN $5\n                    ELSE description\n                END,\n                visibility = COALESCE($6, visibility)\n            WHERE id = $1 AND user_id = $2\n            RETURNING\n                id, user_id, title, description,\n                storage_backend, storage_profile, storage_key,\n                content_type, file_size, status, visibility,\n                trashed_at, archived_at, created_at, updated_at\n            ",
  "describe": {
    "columns": [
      {
        "ordinal": 0,
        "name": "id",
        "type_info": "Uuid"
      },
      {
        "ordinal": 1,
        "name": "user_id",
        "type_info": "Uuid"
      },
      {
        "ordinal": 2,
        "name": "title",
        "type_info": "Varchar"
      },
      {
        "ordinal": 3,
        "name": "description",
        "type_info": "Text"
      },
      {
        "ordinal": 4,
        "name": "storage_backend",
        "type_info": "Text"
      },
      {
        "ordinal": 5,
        "name": "storage_profile",
        "type_info": "Text"
      },
      {
        "ordinal": 6,
        "name": "storage_key",
        "type_info": "Text"
      },
      {
        "ordinal": 7,
        "name": "content_type",
        "type_info": "Varchar"
      },
      {
        "ordinal": 8,
        "name": "file_size",
        "type_info": "Int8"
      },
      {
        "ordinal": 9,
        "name": "status",
        "type_info": "Varchar"
      },
      {
        "ordinal": 10,
        "name": "visibility",
        "type_info": "Varchar"
      },
      {
        "ordinal": 11,
        "name": "trashed_at",
        "type_info": "Timestamptz"
      },
      {
        "ordinal": 12,
        "name": "archived_at",
        "type_info": "Timestamptz"
      },
      {
        "ordinal": 13,
        "name": "created_at",
        "type_info": "Timestamptz"
      },
      {
        "ordinal": 14,
        "name": "updated_at",
        "type_info": "Timestamptz"
      }
    ],
    "parameters": {
      "Left": [
        "Uuid",
        "Uuid",
        "Varchar",
        "Bool",
        "Text",
        "Varchar"
      ]
    },
    "nullable": [
      false,
      false,
      false,
      true,
      false,
      false,
      false,
      false,
      false,
      false,
      false,
      true,
      true,
      false,
      false
    ]
  },
  "hash": "9198b1e4dab7050f2c80ed78416bde12079e00818c1df6d7716a5b29d037861a"
}
